netbox_static_routes_communities/__init__.py
netbox_static_routes_communities/filtersets.py
netbox_static_routes_communities/forms.py
netbox_static_routes_communities/import_forms.py
netbox_static_routes_communities/models.py
netbox_static_routes_communities/navigation.py
netbox_static_routes_communities/search.py
netbox_static_routes_communities/tables.py
netbox_static_routes_communities/urls.py
netbox_static_routes_communities/views.py
netbox_static_routes_communities/api/__init__.py
netbox_static_routes_communities/api/serializers.py
netbox_static_routes_communities/api/urls.py
netbox_static_routes_communities/api/views.py
netbox_static_routes_communities/migrations/0001_initial.py
netbox_static_routes_communities/migrations/__init__.py
netbox_static_routes_communities/templates/netbox_static_routes_communities/aggregate_routed_by.html
netbox_static_routes_communities/templates/netbox_static_routes_communities/community.html
netbox_static_routes_communities/templates/netbox_static_routes_communities/device_static_routes.html
netbox_static_routes_communities/templates/netbox_static_routes_communities/prefix_routed_by.html
netbox_static_routes_communities/templates/netbox_static_routes_communities/staticroute.html
netbox_static_routes_communities-1.2.2.dist-info/licenses/LICENSE
netbox_static_routes_communities-1.2.2.dist-info/licenses/NOTICE
netbox_static_routes_communities-1.2.2.dist-info/METADATA
netbox_static_routes_communities-1.2.2.dist-info/WHEEL
netbox_static_routes_communities-1.2.2.dist-info/top_level.txt
netbox_static_routes_communities-1.2.2.dist-info/RECORD
