Metadata-Version: 2.4
Name: netbox-static-routes-communities
Version: 1.2.2
Summary: Display static routes in NetBox
Author-email: Marlon Sieker <Marlon.Sieker@tkrz.de>
License: 
Project-URL: Homepage, https://github.com/MarlonSieker/netbox-static-routes-communities
Project-URL: Issues, https://github.com/MarlonSieker/netbox-static-routes-communities/issues
Classifier: Operating System :: OS Independent
Classifier: Programming Language :: Python :: 3
Classifier: Programming Language :: Python :: 3 :: Only
Classifier: Programming Language :: Python :: 3.10
Classifier: Programming Language :: Python :: 3.11
Classifier: Programming Language :: Python :: 3.12
License-File: LICENSE
License-File: NOTICE
Dynamic: license-file
